MANIFEST.in
README.rst
TITLE.txt
lh-agpl3-LICENSE.txt
setup.py
unisos/__init__.py
unisos.wsf.egg-info/PKG-INFO
unisos.wsf.egg-info/SOURCES.txt
unisos.wsf.egg-info/dependency_links.txt
unisos.wsf.egg-info/namespace_packages.txt
unisos.wsf.egg-info/not-zip-safe
unisos.wsf.egg-info/requires.txt
unisos.wsf.egg-info/top_level.txt
unisos/wsf/__init__.py
unisos/wsf/wsf_common.py
unisos/wsf/wsf_config.py
unisos/wsf/wsf_digestHtml.py
unisos/wsf/wsf_inputs.py
unisos/wsf/wsf_parallelProc.py
unisos/wsf/wsf_results.py
unisos/wsf/wsf_scraperBasic.py
unisos/wsf/wsf_scraperMultipage.py